docpull/__init__.py
docpull/__main__.py
docpull/cli.py
docpull/doctor.py
docpull/logging_config.py
docpull/metadata_extractor.py
docpull/py.typed
docpull/cache/__init__.py
docpull/cache/manager.py
docpull/cache/streaming_dedup.py
docpull/concurrency/__init__.py
docpull/concurrency/browser_pool.py
docpull/concurrency/manager.py
docpull/conversion/__init__.py
docpull/conversion/extractor.py
docpull/conversion/markdown.py
docpull/conversion/protocols.py
docpull/core/__init__.py
docpull/core/fetcher.py
docpull/discovery/__init__.py
docpull/discovery/composite.py
docpull/discovery/crawler.py
docpull/discovery/filters.py
docpull/discovery/protocols.py
docpull/discovery/sitemap.py
docpull/discovery/link_extractors/__init__.py
docpull/discovery/link_extractors/browser.py
docpull/discovery/link_extractors/enhanced.py
docpull/discovery/link_extractors/protocols.py
docpull/discovery/link_extractors/static.py
docpull/http/__init__.py
docpull/http/client.py
docpull/http/protocols.py
docpull/http/rate_limiter.py
docpull/models/__init__.py
docpull/models/config.py
docpull/models/events.py
docpull/models/profiles.py
docpull/pipeline/__init__.py
docpull/pipeline/base.py
docpull/pipeline/steps/__init__.py
docpull/pipeline/steps/browser_fetch.py
docpull/pipeline/steps/convert.py
docpull/pipeline/steps/dedup.py
docpull/pipeline/steps/fetch.py
docpull/pipeline/steps/metadata.py
docpull/pipeline/steps/save.py
docpull/pipeline/steps/save_json.py
docpull/pipeline/steps/save_sqlite.py
docpull/pipeline/steps/validate.py
docpull/security/__init__.py
docpull/security/robots.py
docpull/security/url_validator.py
docpull-2.2.0.dist-info/licenses/LICENSE
docpull-2.2.0.dist-info/METADATA
docpull-2.2.0.dist-info/WHEEL
docpull-2.2.0.dist-info/entry_points.txt
docpull-2.2.0.dist-info/top_level.txt
docpull-2.2.0.dist-info/RECORD
