Metadata-Version: 2.4
Name: docpull
Version: 2.2.0
Summary: Pull documentation from the web and convert to clean markdown
Author-email: Zachary Roth <support@raintree.technology>
Maintainer-email: Raintree Technology <support@raintree.technology>
License-Expression: MIT
Project-URL: Homepage, https://github.com/raintree-technology/docpull
Project-URL: Documentation, https://github.com/raintree-technology/docpull#readme
Project-URL: Repository, https://github.com/raintree-technology/docpull
Project-URL: Source Code, https://github.com/raintree-technology/docpull
Project-URL: Bug Tracker, https://github.com/raintree-technology/docpull/issues
Project-URL: Releases, https://github.com/raintree-technology/docpull/releases
Keywords: python,markdown,documentation,web-scraping,developer-tools,claude,ai-training-data
Classifier: Development Status :: 5 - Production/Stable
Classifier: Intended Audience :: Developers
Classifier: Intended Audience :: Information Technology
Classifier: Intended Audience :: Science/Research
Classifier: Intended Audience :: Education
Classifier: Environment :: Console
Classifier: Topic :: Documentation
Classifier: Topic :: Internet :: WWW/HTTP :: Indexing/Search
Classifier: Topic :: Software Development :: Documentation
Classifier: Topic :: Text Processing :: Markup :: HTML
Classifier: Topic :: Text Processing :: Markup :: Markdown
Classifier: Topic :: Utilities
Classifier: Topic :: Scientific/Engineering :: Artificial Intelligence
Classifier: Natural Language :: English
Classifier: Operating System :: OS Independent
Classifier: Programming Language :: Python :: 3
Classifier: Programming Language :: Python :: 3.9
Classifier: Programming Language :: Python :: 3.10
Classifier: Programming Language :: Python :: 3.11
Classifier: Programming Language :: Python :: 3.12
Classifier: Programming Language :: Python :: 3.13
Classifier: Programming Language :: Python :: 3.14
Classifier: Programming Language :: Python :: 3 :: Only
Classifier: Typing :: Typed
Requires-Python: >=3.10
License-File: LICENSE
Requires-Dist: requests>=2.31.0
Requires-Dist: beautifulsoup4>=4.12.0
Requires-Dist: html2text>=2020.1.16
Requires-Dist: defusedxml>=0.7.1
Requires-Dist: extruct>=0.15.0
Requires-Dist: aiohttp>=3.9.0
Requires-Dist: rich>=13.0.0
Requires-Dist: pyyaml>=6.0
Requires-Dist: gitpython>=3.1.40
Requires-Dist: pydantic>=2.0
Provides-Extra: js
Requires-Dist: playwright>=1.40.0; extra == "js"
Provides-Extra: proxy
Requires-Dist: aiohttp-socks>=0.8.0; extra == "proxy"
Provides-Extra: normalize
Requires-Dist: url-normalize>=1.4.0; extra == "normalize"
Provides-Extra: all
Requires-Dist: playwright>=1.40.0; extra == "all"
Requires-Dist: aiohttp-socks>=0.8.0; extra == "all"
Requires-Dist: url-normalize>=1.4.0; extra == "all"
Provides-Extra: dev
Requires-Dist: pytest>=7.0.0; extra == "dev"
Requires-Dist: pytest-cov>=4.0.0; extra == "dev"
Requires-Dist: pytest-asyncio>=0.21.0; extra == "dev"
Requires-Dist: black>=23.0.0; extra == "dev"
Requires-Dist: mypy>=1.0.0; extra == "dev"
Requires-Dist: ruff>=0.1.0; extra == "dev"
Requires-Dist: bandit>=1.7.0; extra == "dev"
Requires-Dist: pip-audit>=2.0.0; extra == "dev"
Requires-Dist: pre-commit>=3.0.0; extra == "dev"
Requires-Dist: types-requests>=2.31.0; extra == "dev"
Requires-Dist: types-beautifulsoup4>=4.12.0; extra == "dev"
Requires-Dist: types-defusedxml>=0.7.0; extra == "dev"
Requires-Dist: types-pyyaml>=6.0.0; extra == "dev"
Dynamic: license-file
